[
    {
        "_id": { "$oid": "674c64a314a5b126f6af7590" },
        "images": [
            "1.jpg"
        ],
        "id": "674c64a314a5b126f6af7590"
    },
    {
        "_id": { "$oid": "674c64a314a5b126f6af7591" },
        "images": [
            "2.jpg"
        ],
        "id": "674c64a314a5b126f6af7591"
    },
    {
        "_id": { "$oid": "674c64a314a5b126f6af7592" },
        "images": [
            "3.jpg"
        ],
        "id": "674c64a314a5b126f6af7592"
    },
    {
        "_id": { "$oid": "674c64a314a5b126f6af7593" },
        "images": [
            "4.jpg"
        ],
        "id": "674c64a314a5b126f6af7593"
    },
    {
        "_id": { "$oid": "674c64a314a5b126f6af7594" },
        "images": [
            "5.jpg"
        ],
        "id": "674c64a314a5b126f6af7594"
    },
    {
        "_id": { "$oid": "674c64a314a5b126f6af7595" },
        "images": [
            "6.jpg"
        ],
        "id": "674c64a314a5b126f6af7595"
    },
    {
        "_id": { "$oid": "674c64a314a5b126f6af7596" },
        "images": [
            "7.jpg"
        ],
        "id": "674c64a314a5b126f6af7596"
    },
    {
        "_id": { "$oid": "674c64a314a5b126f6af7597" },
        "images": [
            "8.jpg"
        ],
        "id": "674c64a314a5b126f6af7597"
    },
    {
        "_id": { "$oid": "674c64a314a5b126f6af7598" },
        "images": [
            "9.jpg"
        ],
        "id": "674c64a314a5b126f6af7598"
    },
    {
        "_id": { "$oid": "674c64a314a5b126f6af7599" },
        "images": [
            "10.jpg"
        ],
        "id": "674c64a314a5b126f6af7599"
    },
    {
        "_id": { "$oid": "674c64a314a5b126f6af759a" },
        "images": [
            "11.jpg"
        ],
        "id": "674c64a314a5b126f6af759a"
    }
]